kiwi_cogs/__init__.py
kiwi_cogs/event.py
kiwi_cogs/exceptions.py
kiwi_cogs/machine.py
kiwi_cogs/state.py
kiwi_cogs/transition.py
kiwi_cogs/utils.py
kiwi_cogs-0.1.2.dist-info/LICENSE
kiwi_cogs-0.1.2.dist-info/METADATA
kiwi_cogs-0.1.2.dist-info/WHEEL
kiwi_cogs-0.1.2.dist-info/RECORD
