Metadata-Version: 2.1
Name: kiwi-cogs
Version: 0.1.2
Summary: A simple and easy to use state machine library 
Home-page: https://github.com/mopeyjellyfish/KiwiCogs/
Author: David Hall
Author-email: dev@davidhall.tech
Requires-Python: >=3.8,<4.0
Classifier: Programming Language :: Python :: 3
Classifier: Programming Language :: Python :: 3.8
Classifier: Programming Language :: Python :: 3.9
Classifier: Programming Language :: Python :: 3.10
Classifier: Programming Language :: Python :: 3.11
Requires-Dist: pydantic (>=1.10.8,<2.0.0)
Project-URL: Documentation, https://mopeyjellyfish.github.io/KiwiCogs/
Project-URL: Repository, https://github.com/mopeyjellyfish/KiwiCogs/
